rest_in_peace/__init__.py
rest_in_peace/cli.py
rest_in_peace/database.py
rest_in_peace/openapi.py
rest_in_peace/server.py
Rest_In_Peace-0.3.2.dist-info/LICENSE
Rest_In_Peace-0.3.2.dist-info/METADATA
Rest_In_Peace-0.3.2.dist-info/WHEEL
Rest_In_Peace-0.3.2.dist-info/entry_points.txt
Rest_In_Peace-0.3.2.dist-info/top_level.txt
Rest_In_Peace-0.3.2.dist-info/RECORD
