Metadata-Version: 2.1
Name: Rest-In-Peace
Version: 0.3.2
Summary: An instant and schemaless rest api with sqlite
Home-page: https://github.com/henriquegogo/rest_in_peace
Author: Henrique Gogó
Author-email: henriquegogo@gmail.com
License: MIT
Project-URL: Bug Tracker, https://github.com/henriquegogo/rest_in_peace/issues
Platform: UNKNOWN
Classifier: Programming Language :: Python :: 3
Classifier: License :: OSI Approved :: MIT License
Classifier: Operating System :: OS Independent
Requires-Python: >=3.6
License-File: LICENSE
